Metadata-Version: 2.1
Name: wait-notify
Version: 0.1.0
Summary: Batch job submission and management tool
Home-page: http://github.com/paulgessinger/wait-notify
Author: Paul Gessinger
Author-email: hello@paulgessinger.com
License: MIT
Platform: UNKNOWN
Provides-Extra: dev
Provides-Extra: ipython
Provides-Extra: test
